{
  "img_id": "cla820glqs4tr071u8yh6havq",
  "class": "ulcerative_colitis",
  "prediction": 0.9905310273170471,
  "all_predictions": {
    "oesophagitis": 2.0782624210978484e-13,
    "cecum": 0.9955390095710754,
    "irrelaevnat": 1.649696486083485e-07,
    "z_line": 2.8210900282488183e-10,
    "polyp": 0.29989945888519287,
    "ulcerative_colitis": 0.9905310273170471
  },
  "regions": [
    {
      "bbox": [
        400,
        128,
        272,
        435
      ],
      "area": 65662
    },
    {
      "bbox": [
        43,
        49,
        245,
        217
      ],
      "area": 32927
    }
  ]
}