{
  "img_id": "clb0kvxvw91b4074yevpk430g",
  "class": "oesophagitis",
  "prediction": 0.9999496936798096,
  "all_predictions": {
    "oesophagitis": 0.9999496936798096,
    "cecum": 9.403256819029426e-12,
    "irrelaevnat": 6.380667105787552e-09,
    "z_line": 2.228589361663591e-11,
    "polyp": 2.5362958955277293e-10,
    "ulcerative_colitis": 0.0004846300289500505
  },
  "regions": [
    {
      "bbox": [
        382,
        232,
        601,
        423
      ],
      "area": 168749
    }
  ]
}