{
  "img_id": "cla820gmos62z071uatxb81v4",
  "class": "ulcerative_colitis",
  "prediction": 0.0022667287848889828,
  "all_predictions": {
    "oesophagitis": 7.198861388427543e-22,
    "cecum": 1.2547733338742301e-31,
    "irrelaevnat": 3.3609084389917394e-23,
    "z_line": 6.775309573831839e-21,
    "polyp": 0.004317175596952438,
    "ulcerative_colitis": 0.0022667287848889828
  },
  "regions": [
    {
      "bbox": [
        259,
        95,
        293,
        259
      ],
      "area": 45359
    }
  ]
}