{
  "img_id": "cla820gmls5y7071u6sa46fd2",
  "class": "ulcerative_colitis",
  "prediction": 0.9999985694885254,
  "all_predictions": {
    "oesophagitis": 6.123122295758124e-16,
    "cecum": 1.5957464238880448e-09,
    "irrelaevnat": 3.5108506503343434e-17,
    "z_line": 4.780141309118641e-19,
    "polyp": 0.9999876022338867,
    "ulcerative_colitis": 0.9999985694885254
  },
  "regions": [
    {
      "bbox": [
        125,
        129,
        531,
        432
      ],
      "area": 118888
    }
  ]
}