{
  "img_id": "clb0kvxwq92m0074ye2ii2wbs",
  "class": "z_line",
  "prediction": 0.9995799660682678,
  "all_predictions": {
    "oesophagitis": 0.40022948384284973,
    "cecum": 7.808031022953077e-15,
    "irrelaevnat": 9.502365827529502e-08,
    "z_line": 0.9995799660682678,
    "polyp": 6.89626078465011e-10,
    "ulcerative_colitis": 3.637546146050387e-15
  },
  "regions": [
    {
      "bbox": [
        173,
        388,
        482,
        506
      ],
      "area": 188133
    },
    {
      "bbox": [
        781,
        164,
        275,
        166
      ],
      "area": 33444
    }
  ]
}