{
  "img_id": "clb0kvxv59034074y3mvo42nw",
  "class": "oesophagitis",
  "prediction": 0.4904322922229767,
  "all_predictions": {
    "oesophagitis": 0.4904322922229767,
    "cecum": 4.31113955298712e-12,
    "irrelaevnat": 2.825662477334845e-06,
    "z_line": 0.9426519870758057,
    "polyp": 3.617435517799805e-10,
    "ulcerative_colitis": 8.040805710152199e-07
  },
  "regions": [
    {
      "bbox": [
        256,
        108,
        821,
        447
      ],
      "area": 220349
    },
    {
      "bbox": [
        552,
        567,
        416,
        162
      ],
      "area": 52311
    },
    {
      "bbox": [
        1110,
        482,
        136,
        129
      ],
      "area": 13898
    }
  ]
}