{
  "img_id": "clb0kvxux8ztk074ydrosfmn4",
  "class": "z_line",
  "prediction": 0.024221306666731834,
  "all_predictions": {
    "oesophagitis": 0.9992196559906006,
    "cecum": 9.298022907167081e-10,
    "irrelaevnat": 1.4201341400621459e-05,
    "z_line": 0.024221306666731834,
    "polyp": 1.9473254952995234e-10,
    "ulcerative_colitis": 5.323737894968872e-09
  },
  "regions": [
    {
      "bbox": [
        369,
        0,
        357,
        247
      ],
      "area": 77734
    },
    {
      "bbox": [
        0,
        709,
        362,
        315
      ],
      "area": 71350
    },
    {
      "bbox": [
        0,
        95,
        212,
        199
      ],
      "area": 31502
    }
  ]
}