{
  "img_id": "clb0kvxwf923o074ybccw0pgg",
  "class": "oesophagitis",
  "prediction": 0.9999802112579346,
  "all_predictions": {
    "oesophagitis": 0.9999802112579346,
    "cecum": 2.3207678834236134e-11,
    "irrelaevnat": 1.776699355104938e-05,
    "z_line": 0.09516026824712753,
    "polyp": 7.2492181528438504e-12,
    "ulcerative_colitis": 2.925172604140158e-10
  },
  "regions": [
    {
      "bbox": [
        839,
        130,
        407,
        718
      ],
      "area": 182944
    },
    {
      "bbox": [
        403,
        177,
        320,
        169
      ],
      "area": 38148
    }
  ]
}