{
  "img_id": "clb0kvxvr914c074y6x1p6j5z",
  "class": "z_line",
  "prediction": 0.9995050430297852,
  "all_predictions": {
    "oesophagitis": 0.001527237007394433,
    "cecum": 9.578714435672618e-17,
    "irrelaevnat": 7.679544751226786e-07,
    "z_line": 0.9995050430297852,
    "polyp": 1.4532277291257056e-11,
    "ulcerative_colitis": 6.235590250527542e-14
  },
  "regions": [
    {
      "bbox": [
        224,
        242,
        380,
        457
      ],
      "area": 125783
    },
    {
      "bbox": [
        890,
        190,
        166,
        351
      ],
      "area": 38888
    }
  ]
}