{
  "img_id": "clb0kvxuv8zrk074ye0xpeup4",
  "class": "z_line",
  "prediction": 0.01705983094871044,
  "all_predictions": {
    "oesophagitis": 0.9964479207992554,
    "cecum": 5.337528565695559e-15,
    "irrelaevnat": 1.198298491544847e-07,
    "z_line": 0.01705983094871044,
    "polyp": 1.477041333686202e-08,
    "ulcerative_colitis": 4.536509582158017e-14
  },
  "regions": [
    {
      "bbox": [
        734,
        0,
        361,
        289
      ],
      "area": 57202
    },
    {
      "bbox": [
        152,
        497,
        213,
        276
      ],
      "area": 37826
    },
    {
      "bbox": [
        47,
        0,
        160,
        209
      ],
      "area": 12805
    },
    {
      "bbox": [
        417,
        930,
        58,
        87
      ],
      "area": 4369
    }
  ]
}